gen/__init__.py
gen/fodcatLexer.py
gen/fodcatListener.py
gen/fodcatParser.py
gen/fodcatVisitor.py
lieGenTools-0.1.1.dist-info/LICENSE
lieGenTools-0.1.1.dist-info/METADATA
lieGenTools-0.1.1.dist-info/WHEEL
lieGenTools-0.1.1.dist-info/top_level.txt
lieGenTools-0.1.1.dist-info/RECORD
