Metadata-Version: 2.1
Name: lieGenTools
Version: 0.1.1
Summary: A Package
Author: SoftLab
Author-email: 
License: MIT
Platform: UNKNOWN
License-File: LICENSE
Requires-Dist: antlr4-python3-runtime
